lightwave/__init__.py
lightwave/ai/__init__.py
lightwave/ai/base.py
lightwave/ai/brand_context.py
lightwave/ai/copywriter.py
lightwave/ai/handlers.py
lightwave/ai/permissions.py
lightwave/ai/types.py
lightwave/ai/tools/__init__.py
lightwave/ai/tools/admin_db.py
lightwave/ai/tools/email.py
lightwave/ai/tools/weather.py
lightwave/auth/__init__.py
lightwave/auth/helpers.py
lightwave/auth/models.py
lightwave/auth/serializers.py
lightwave/auth/signals.py
lightwave/chat/__init__.py
lightwave/chat/models.py
lightwave/cms/__init__.py
lightwave/cms/admin.py
lightwave/cms/cache.py
lightwave/cms/hero.py
lightwave/cms/models.py
lightwave/cms/renderers.py
lightwave/cms/serializers.py
lightwave/cms/signals.py
lightwave/cms/urls.py
lightwave/cms/views.py
lightwave/cms/management/__init__.py
lightwave/cms/management/commands/__init__.py
lightwave/cms/management/commands/sync_cms_cache.py
lightwave/cms/templatetags/__init__.py
lightwave/cms/templatetags/cms_tags.py
lightwave/islands/__init__.py
lightwave/islands/apps.py
lightwave/islands/config.py
lightwave/islands/context_processors.py
lightwave/islands/middleware.py
lightwave/islands/navigation.py
lightwave/islands/templates/lightwave/islands/footer.html
lightwave/islands/templates/lightwave/islands/header.html
lightwave/islands/templates/lightwave/islands/toast.html
lightwave/islands/templates/lightwave/layouts/app.html
lightwave/islands/templates/lightwave/layouts/base.html
lightwave/islands/templates/lightwave/layouts/site.html
lightwave/islands/templatetags/__init__.py
lightwave/islands/templatetags/island_tags.py
lightwave/security/__init__.py
lightwave/security/apps.py
lightwave/security/middleware.py
lightwave/storage/__init__.py
lightwave/storage/backends.py
lightwave/utils/__init__.py
lightwave/utils/billing.py
lightwave/utils/models.py
lightwave/utils/slug.py
lightwave/utils/timezones.py
lightwave_core-0.3.2.dist-info/METADATA
lightwave_core-0.3.2.dist-info/WHEEL
lightwave_core-0.3.2.dist-info/RECORD
