Metadata-Version: 2.4
Name: lightwave-core
Version: 0.3.2
Summary: Shared Django utilities for LightWave Media projects
Requires-Python: >=3.12
Requires-Dist: django-storages[s3]>=1.14
Requires-Dist: django>=4.2
Requires-Dist: djangorestframework>=3.14
Requires-Dist: pillow>=10.0
Requires-Dist: pyyaml>=6.0
Provides-Extra: billing
Requires-Dist: dj-stripe>=2.8; extra == 'billing'
Provides-Extra: dev
Requires-Dist: pytest-django>=4.5; extra == 'dev'
Requires-Dist: pytest>=8.0; extra == 'dev'
Provides-Extra: quickbooks
Requires-Dist: intuit-oauth>=1.2; extra == 'quickbooks'
Requires-Dist: python-quickbooks>=0.9; extra == 'quickbooks'
